{
  "grid_factor_kg_per_kwh": 0.4243,
  "source": "Climatiq TR grid factor 2023 — supersedable by EPİAŞ Şeffaflık hourly",
  "per_facility": [
    {
      "facility_id": "isdemir-iskenderun",
      "operator": "İsdemir",
      "sector": "steel",
      "production_estimate_t": 3180000.0,
      "elec_intensity_kwh_per_t": 400,
      "scope2_estimate_t": 539709.6,
      "scope1_disclosed_t": 10663364.0,
      "scope12_total_t": 11203073.6,
      "scope2_share_pct": 4.817513650896661
    },
    {
      "facility_id": "erdemir-eregli",
      "operator": "Erdemir",
      "sector": "steel",
      "production_estimate_t": 2400000.0,
      "elec_intensity_kwh_per_t": 400,
      "scope2_estimate_t": 407328.0,
      "scope1_disclosed_t": 6667232.0,
      "scope12_total_t": 7074560.0,
      "scope2_share_pct": 5.757644291659128
    },
    {
      "facility_id": "kardemir-karabuk",
      "operator": "Kardemir",
      "sector": "steel",
      "production_estimate_t": 2100000.0,
      "elec_intensity_kwh_per_t": 400,
      "scope2_estimate_t": 356412.0,
      "scope1_disclosed_t": 5650626.0,
      "scope12_total_t": 6007038.0,
      "scope2_share_pct": 5.933240309117405
    },
    {
      "facility_id": "nuh-hereke",
      "operator": "Nuh Çimento",
      "sector": "cement",
      "production_estimate_t": 3420000.0,
      "elec_intensity_kwh_per_t": 110,
      "scope2_estimate_t": 159621.66,
      "scope1_disclosed_t": 3584953.0,
      "scope12_total_t": 3744574.66,
      "scope2_share_pct": 4.2627447572376616
    },
    {
      "facility_id": "akcansa-canakkale",
      "operator": "Akçansa",
      "sector": "cement",
      "production_estimate_t": 3300000.0,
      "elec_intensity_kwh_per_t": 110,
      "scope2_estimate_t": 154020.9,
      "scope1_disclosed_t": 3466000.0,
      "scope12_total_t": 3620020.9,
      "scope2_share_pct": 4.254696430067572
    },
    {
      "facility_id": "goltas-isparta",
      "operator": "Göltaş Çimento",
      "sector": "cement",
      "production_estimate_t": 3000000.0,
      "elec_intensity_kwh_per_t": 110,
      "scope2_estimate_t": 140019.0,
      "scope1_disclosed_t": 1669072.0,
      "scope12_total_t": 1809091.0,
      "scope2_share_pct": 7.739743329661139
    },
    {
      "facility_id": "batisoke-soke",
      "operator": "Batısöke Söke Çimento",
      "sector": "cement",
      "production_estimate_t": 2400000.0,
      "elec_intensity_kwh_per_t": 110,
      "scope2_estimate_t": 112015.2,
      "scope1_disclosed_t": 1577926.0,
      "scope12_total_t": 1689941.2,
      "scope2_share_pct": 6.628348962673967
    },
    {
      "facility_id": "akcansa-buyukcekmece",
      "operator": "Akçansa",
      "sector": "cement",
      "production_estimate_t": 1500000.0,
      "elec_intensity_kwh_per_t": 110,
      "scope2_estimate_t": 70009.5,
      "scope1_disclosed_t": 1514000.0,
      "scope12_total_t": 1584009.5,
      "scope2_share_pct": 4.419765159236735
    },
    {
      "facility_id": "habas-aliaga",
      "operator": "Habaş",
      "sector": "steel",
      "production_estimate_t": 2700000.0,
      "elec_intensity_kwh_per_t": 600,
      "scope2_estimate_t": 687366.0,
      "scope1_disclosed_t": 830338.0,
      "scope12_total_t": 1517704.0,
      "scope2_share_pct": 45.28985889211599
    },
    {
      "facility_id": "colakoglu-gebze",
      "operator": "Çolakoğlu",
      "sector": "steel",
      "production_estimate_t": 2700000.0,
      "elec_intensity_kwh_per_t": 600,
      "scope2_estimate_t": 687366.0,
      "scope1_disclosed_t": 566519.0,
      "scope12_total_t": 1253885.0,
      "scope2_share_pct": 54.818902849942376
    },
    {
      "facility_id": "afyon-cimento",
      "operator": "Afyon Çimento",
      "sector": "cement",
      "production_estimate_t": 1080000.0,
      "elec_intensity_kwh_per_t": 110,
      "scope2_estimate_t": 50406.84,
      "scope1_disclosed_t": 1200000.0,
      "scope12_total_t": 1250406.84,
      "scope2_share_pct": 4.031235145834614
    },
    {
      "facility_id": "bursa-cimento",
      "operator": "Bursa Çimento",
      "sector": "cement",
      "production_estimate_t": 1200000.0,
      "elec_intensity_kwh_per_t": 110,
      "scope2_estimate_t": 56007.6,
      "scope1_disclosed_t": 1121545.0,
      "scope12_total_t": 1177552.6,
      "scope2_share_pct": 4.756271609438083
    },
    {
      "facility_id": "tosyali-osmaniye",
      "operator": "Tosyalı",
      "sector": "steel",
      "production_estimate_t": 2100000.0,
      "elec_intensity_kwh_per_t": 800,
      "scope2_estimate_t": 712824.0,
      "scope1_disclosed_t": 0,
      "scope12_total_t": 712824.0,
      "scope2_share_pct": 100.0
    },
    {
      "facility_id": "icdas-biga",
      "operator": "İçdaş",
      "sector": "steel",
      "production_estimate_t": 2100000.0,
      "elec_intensity_kwh_per_t": 600,
      "scope2_estimate_t": 534618.0,
      "scope1_disclosed_t": 0,
      "scope12_total_t": 534618.0,
      "scope2_share_pct": 100.0
    },
    {
      "facility_id": "akcansa-ladik",
      "operator": "Akçansa",
      "sector": "cement",
      "production_estimate_t": 600000.0,
      "elec_intensity_kwh_per_t": 110,
      "scope2_estimate_t": 28003.8,
      "scope1_disclosed_t": 499000.0,
      "scope12_total_t": 527003.8,
      "scope2_share_pct": 5.313775726095333
    },
    {
      "facility_id": "izdemir-aliaga",
      "operator": "İzdemir",
      "sector": "steel",
      "production_estimate_t": 900000.0,
      "elec_intensity_kwh_per_t": 600,
      "scope2_estimate_t": 229122.0,
      "scope1_disclosed_t": 271123.0,
      "scope12_total_t": 500245.0,
      "scope2_share_pct": 45.80195704104988
    },
    {
      "facility_id": "tosyali-iskenderun",
      "operator": "Tosyalı",
      "sector": "steel",
      "production_estimate_t": 1800000.0,
      "elec_intensity_kwh_per_t": 600,
      "scope2_estimate_t": 458244.0,
      "scope1_disclosed_t": 0,
      "scope12_total_t": 458244.0,
      "scope2_share_pct": 100.0
    },
    {
      "facility_id": "toros-mersin",
      "operator": "Toros Tarım",
      "sector": "fertilizer",
      "production_estimate_t": 486000.0,
      "elec_intensity_kwh_per_t": 80,
      "scope2_estimate_t": 16496.784,
      "scope1_disclosed_t": 383150.0,
      "scope12_total_t": 399646.784,
      "scope2_share_pct": 4.127841048759697
    },
    {
      "facility_id": "ekinciler-iskenderun",
      "operator": "Ekinciler",
      "sector": "steel",
      "production_estimate_t": 1200000.0,
      "elec_intensity_kwh_per_t": 600,
      "scope2_estimate_t": 305496.0,
      "scope1_disclosed_t": 0,
      "scope12_total_t": 305496.0,
      "scope2_share_pct": 100.0
    },
    {
      "facility_id": "diler-aliaga",
      "operator": "Diler",
      "sector": "steel",
      "production_estimate_t": 1200000.0,
      "elec_intensity_kwh_per_t": 600,
      "scope2_estimate_t": 305496.0,
      "scope1_disclosed_t": 0,
      "scope12_total_t": 305496.0,
      "scope2_share_pct": 100.0
    },
    {
      "facility_id": "eti-aluminyum-seydisehir",
      "operator": "Eti Alüminyum",
      "sector": "aluminum",
      "production_estimate_t": 48000.0,
      "elec_intensity_kwh_per_t": 14000,
      "scope2_estimate_t": 285129.6,
      "scope1_disclosed_t": 0,
      "scope12_total_t": 285129.6,
      "scope2_share_pct": 100.0
    },
    {
      "facility_id": "toros-samsun",
      "operator": "Toros Tarım",
      "sector": "fertilizer",
      "production_estimate_t": 345000.0,
      "elec_intensity_kwh_per_t": 80,
      "scope2_estimate_t": 11710.68,
      "scope1_disclosed_t": 255180.0,
      "scope12_total_t": 266890.68,
      "scope2_share_pct": 4.387819012638433
    },
    {
      "facility_id": "tosyali-sivas",
      "operator": "Tosyalı",
      "sector": "steel",
      "production_estimate_t": 900000.0,
      "elec_intensity_kwh_per_t": 600,
      "scope2_estimate_t": 229122.0,
      "scope1_disclosed_t": 0,
      "scope12_total_t": 229122.0,
      "scope2_share_pct": 100.0
    },
    {
      "facility_id": "toros-ceyhan",
      "operator": "Toros Tarım",
      "sector": "fertilizer",
      "production_estimate_t": 493020.0,
      "elec_intensity_kwh_per_t": 80,
      "scope2_estimate_t": 16735.07088,
      "scope1_disclosed_t": 203840.0,
      "scope12_total_t": 220575.07088,
      "scope2_share_pct": 7.587018248813992
    },
    {
      "facility_id": "borcelik-gemlik",
      "operator": "Borçelik",
      "sector": "steel",
      "production_estimate_t": 600000.0,
      "elec_intensity_kwh_per_t": 600,
      "scope2_estimate_t": 152748.0,
      "scope1_disclosed_t": 0,
      "scope12_total_t": 152748.0,
      "scope2_share_pct": 100.0
    },
    {
      "facility_id": "kroman-gebze",
      "operator": "Kroman Çelik",
      "sector": "steel",
      "production_estimate_t": 600000.0,
      "elec_intensity_kwh_per_t": 600,
      "scope2_estimate_t": 152748.0,
      "scope1_disclosed_t": 0,
      "scope12_total_t": 152748.0,
      "scope2_share_pct": 100.0
    },
    {
      "facility_id": "asilcelik-izmit",
      "operator": "Asilçelik",
      "sector": "steel",
      "production_estimate_t": 600000.0,
      "elec_intensity_kwh_per_t": 600,
      "scope2_estimate_t": 152748.0,
      "scope1_disclosed_t": 0,
      "scope12_total_t": 152748.0,
      "scope2_share_pct": 100.0
    },
    {
      "facility_id": "yazici-iskenderun",
      "operator": "Yazıcı Demir Çelik",
      "sector": "steel",
      "production_estimate_t": 600000.0,
      "elec_intensity_kwh_per_t": 600,
      "scope2_estimate_t": 152748.0,
      "scope1_disclosed_t": 0,
      "scope12_total_t": 152748.0,
      "scope2_share_pct": 100.0
    },
    {
      "facility_id": "assan-tuzla",
      "operator": "Assan Alüminyum",
      "sector": "aluminum",
      "production_estimate_t": 216000.0,
      "elec_intensity_kwh_per_t": 150,
      "scope2_estimate_t": 13747.32,
      "scope1_disclosed_t": 108500.0,
      "scope12_total_t": 122247.32,
      "scope2_share_pct": 11.245498060816384
    },
    {
      "facility_id": "oyak-bolu",
      "operator": "OYAK Çimento",
      "sector": "cement",
      "production_estimate_t": 2100000.0,
      "elec_intensity_kwh_per_t": 110,
      "scope2_estimate_t": 98013.3,
      "scope1_disclosed_t": 0,
      "scope12_total_t": 98013.3,
      "scope2_share_pct": 100.0
    },
    {
      "facility_id": "oyak-adana",
      "operator": "OYAK Çimento",
      "sector": "cement",
      "production_estimate_t": 2100000.0,
      "elec_intensity_kwh_per_t": 110,
      "scope2_estimate_t": 98013.3,
      "scope1_disclosed_t": 0,
      "scope12_total_t": 98013.3,
      "scope2_share_pct": 100.0
    },
    {
      "facility_id": "konya-cimento",
      "operator": "Konya Çimento",
      "sector": "cement",
      "production_estimate_t": 2100000.0,
      "elec_intensity_kwh_per_t": 110,
      "scope2_estimate_t": 98013.3,
      "scope1_disclosed_t": 0,
      "scope12_total_t": 98013.3,
      "scope2_share_pct": 100.0
    },
    {
      "facility_id": "adana-cimento",
      "operator": "Adana Çimento",
      "sector": "cement",
      "production_estimate_t": 2100000.0,
      "elec_intensity_kwh_per_t": 110,
      "scope2_estimate_t": 98013.3,
      "scope1_disclosed_t": 0,
      "scope12_total_t": 98013.3,
      "scope2_share_pct": 100.0
    },
    {
      "facility_id": "oyak-unye",
      "operator": "OYAK Çimento",
      "sector": "cement",
      "production_estimate_t": 1920000.0,
      "elec_intensity_kwh_per_t": 110,
      "scope2_estimate_t": 89612.16,
      "scope1_disclosed_t": 0,
      "scope12_total_t": 89612.16,
      "scope2_share_pct": 100.0
    },
    {
      "facility_id": "oyak-mardin",
      "operator": "OYAK Çimento",
      "sector": "cement",
      "production_estimate_t": 1800000.0,
      "elec_intensity_kwh_per_t": 110,
      "scope2_estimate_t": 84011.4,
      "scope1_disclosed_t": 0,
      "scope12_total_t": 84011.4,
      "scope2_share_pct": 100.0
    },
    {
      "facility_id": "asas-akyazi",
      "operator": "Asaş Alüminyum",
      "sector": "aluminum",
      "production_estimate_t": 150000.0,
      "elec_intensity_kwh_per_t": 150,
      "scope2_estimate_t": 9546.75,
      "scope1_disclosed_t": 68618.0,
      "scope12_total_t": 78164.75,
      "scope2_share_pct": 12.213625707240157
    },
    {
      "facility_id": "limak-ankara",
      "operator": "Limak Çimento",
      "sector": "cement",
      "production_estimate_t": 1500000.0,
      "elec_intensity_kwh_per_t": 110,
      "scope2_estimate_t": 70009.5,
      "scope1_disclosed_t": 0,
      "scope12_total_t": 70009.5,
      "scope2_share_pct": 100.0
    },
    {
      "facility_id": "limak-sanliurfa",
      "operator": "Limak Çimento",
      "sector": "cement",
      "production_estimate_t": 1500000.0,
      "elec_intensity_kwh_per_t": 110,
      "scope2_estimate_t": 70009.5,
      "scope1_disclosed_t": 0,
      "scope12_total_t": 70009.5,
      "scope2_share_pct": 100.0
    },
    {
      "facility_id": "limak-trakya",
      "operator": "Limak Çimento",
      "sector": "cement",
      "production_estimate_t": 1500000.0,
      "elec_intensity_kwh_per_t": 110,
      "scope2_estimate_t": 70009.5,
      "scope1_disclosed_t": 0,
      "scope12_total_t": 70009.5,
      "scope2_share_pct": 100.0
    },
    {
      "facility_id": "cimentas-izmir",
      "operator": "Çimentaş",
      "sector": "cement",
      "production_estimate_t": 1500000.0,
      "elec_intensity_kwh_per_t": 110,
      "scope2_estimate_t": 70009.5,
      "scope1_disclosed_t": 0,
      "scope12_total_t": 70009.5,
      "scope2_share_pct": 100.0
    },
    {
      "facility_id": "denizli-cimento",
      "operator": "Denizli Çimento",
      "sector": "cement",
      "production_estimate_t": 1500000.0,
      "elec_intensity_kwh_per_t": 110,
      "scope2_estimate_t": 70009.5,
      "scope1_disclosed_t": 0,
      "scope12_total_t": 70009.5,
      "scope2_share_pct": 100.0
    },
    {
      "facility_id": "bolu-cimento",
      "operator": "Bolu Çimento",
      "sector": "cement",
      "production_estimate_t": 1500000.0,
      "elec_intensity_kwh_per_t": 110,
      "scope2_estimate_t": 70009.5,
      "scope1_disclosed_t": 0,
      "scope12_total_t": 70009.5,
      "scope2_share_pct": 100.0
    },
    {
      "facility_id": "cimsa-mersin",
      "operator": "Çimsa",
      "sector": "cement",
      "production_estimate_t": 1440000.0,
      "elec_intensity_kwh_per_t": 110,
      "scope2_estimate_t": 67209.12,
      "scope1_disclosed_t": 0,
      "scope12_total_t": 67209.12,
      "scope2_share_pct": 100.0
    },
    {
      "facility_id": "oyak-aslan",
      "operator": "OYAK Çimento",
      "sector": "cement",
      "production_estimate_t": 1200000.0,
      "elec_intensity_kwh_per_t": 110,
      "scope2_estimate_t": 56007.6,
      "scope1_disclosed_t": 0,
      "scope12_total_t": 56007.6,
      "scope2_share_pct": 100.0
    },
    {
      "facility_id": "baticim-izmir",
      "operator": "Batıçim",
      "sector": "cement",
      "production_estimate_t": 1200000.0,
      "elec_intensity_kwh_per_t": 110,
      "scope2_estimate_t": 56007.6,
      "scope1_disclosed_t": 0,
      "scope12_total_t": 56007.6,
      "scope2_share_pct": 100.0
    },
    {
      "facility_id": "cimko-adiyaman",
      "operator": "Çimko",
      "sector": "cement",
      "production_estimate_t": 1200000.0,
      "elec_intensity_kwh_per_t": 110,
      "scope2_estimate_t": 56007.6,
      "scope1_disclosed_t": 0,
      "scope12_total_t": 56007.6,
      "scope2_share_pct": 100.0
    },
    {
      "facility_id": "cimsa-kayseri",
      "operator": "Çimsa",
      "sector": "cement",
      "production_estimate_t": 1020000.0,
      "elec_intensity_kwh_per_t": 110,
      "scope2_estimate_t": 47606.46,
      "scope1_disclosed_t": 0,
      "scope12_total_t": 47606.46,
      "scope2_share_pct": 100.0
    },
    {
      "facility_id": "cimsa-eskisehir",
      "operator": "Çimsa",
      "sector": "cement",
      "production_estimate_t": 900000.0,
      "elec_intensity_kwh_per_t": 110,
      "scope2_estimate_t": 42005.7,
      "scope1_disclosed_t": 0,
      "scope12_total_t": 42005.7,
      "scope2_share_pct": 100.0
    },
    {
      "facility_id": "limak-kurtalan",
      "operator": "Limak Çimento",
      "sector": "cement",
      "production_estimate_t": 900000.0,
      "elec_intensity_kwh_per_t": 110,
      "scope2_estimate_t": 42005.7,
      "scope1_disclosed_t": 0,
      "scope12_total_t": 42005.7,
      "scope2_share_pct": 100.0
    },
    {
      "facility_id": "cimentas-edirne",
      "operator": "Çimentaş",
      "sector": "cement",
      "production_estimate_t": 900000.0,
      "elec_intensity_kwh_per_t": 110,
      "scope2_estimate_t": 42005.7,
      "scope1_disclosed_t": 0,
      "scope12_total_t": 42005.7,
      "scope2_share_pct": 100.0
    },
    {
      "facility_id": "askale-erzurum",
      "operator": "Aşkale Çimento",
      "sector": "cement",
      "production_estimate_t": 900000.0,
      "elec_intensity_kwh_per_t": 110,
      "scope2_estimate_t": 42005.7,
      "scope1_disclosed_t": 0,
      "scope12_total_t": 42005.7,
      "scope2_share_pct": 100.0
    },
    {
      "facility_id": "cimsa-nigde",
      "operator": "Çimsa",
      "sector": "cement",
      "production_estimate_t": 840000.0,
      "elec_intensity_kwh_per_t": 110,
      "scope2_estimate_t": 39205.32,
      "scope1_disclosed_t": 0,
      "scope12_total_t": 39205.32,
      "scope2_share_pct": 100.0
    },
    {
      "facility_id": "limak-ergani",
      "operator": "Limak Çimento",
      "sector": "cement",
      "production_estimate_t": 720000.0,
      "elec_intensity_kwh_per_t": 110,
      "scope2_estimate_t": 33604.56,
      "scope1_disclosed_t": 0,
      "scope12_total_t": 33604.56,
      "scope2_share_pct": 100.0
    },
    {
      "facility_id": "gubretas-izmit",
      "operator": "Gübretaş",
      "sector": "fertilizer",
      "production_estimate_t": 480000.0,
      "elec_intensity_kwh_per_t": 80,
      "scope2_estimate_t": 16293.12,
      "scope1_disclosed_t": 13281.0,
      "scope12_total_t": 29574.120000000003,
      "scope2_share_pct": 55.092493031069054
    },
    {
      "facility_id": "limak-derik",
      "operator": "Limak Çimento",
      "sector": "cement",
      "production_estimate_t": 600000.0,
      "elec_intensity_kwh_per_t": 110,
      "scope2_estimate_t": 28003.8,
      "scope1_disclosed_t": 0,
      "scope12_total_t": 28003.8,
      "scope2_share_pct": 100.0
    },
    {
      "facility_id": "cimentas-elazig",
      "operator": "Çimentaş",
      "sector": "cement",
      "production_estimate_t": 600000.0,
      "elec_intensity_kwh_per_t": 110,
      "scope2_estimate_t": 28003.8,
      "scope1_disclosed_t": 0,
      "scope12_total_t": 28003.8,
      "scope2_share_pct": 100.0
    },
    {
      "facility_id": "bagfas-bandirma",
      "operator": "BAGFAŞ",
      "sector": "fertilizer",
      "production_estimate_t": 420000.0,
      "elec_intensity_kwh_per_t": 80,
      "scope2_estimate_t": 14256.48,
      "scope1_disclosed_t": 9828.0,
      "scope12_total_t": 24084.48,
      "scope2_share_pct": 59.19363839285714
    },
    {
      "facility_id": "limak-bitlis",
      "operator": "Limak Çimento",
      "sector": "cement",
      "production_estimate_t": 480000.0,
      "elec_intensity_kwh_per_t": 110,
      "scope2_estimate_t": 22403.04,
      "scope1_disclosed_t": 0,
      "scope12_total_t": 22403.04,
      "scope2_share_pct": 100.0
    },
    {
      "facility_id": "gemlik-gubre",
      "operator": "Gemlik Gübre",
      "sector": "fertilizer",
      "production_estimate_t": 300000.0,
      "elec_intensity_kwh_per_t": 80,
      "scope2_estimate_t": 10183.2,
      "scope1_disclosed_t": 0,
      "scope12_total_t": 10183.2,
      "scope2_share_pct": 100.0
    }
  ],
  "totals": {
    "scope1_t": 40324095.0,
    "scope2_estimated_t": 8816114.564879999,
    "scope12_total_t": 49140209.56488
  }
}